database_connection/__init__.py
database_connection/csv.py
database_connection/memory.py
wf_database_connection-0.1.1.dist-info/LICENSE
wf_database_connection-0.1.1.dist-info/METADATA
wf_database_connection-0.1.1.dist-info/WHEEL
wf_database_connection-0.1.1.dist-info/top_level.txt
wf_database_connection-0.1.1.dist-info/RECORD
